Metadata-Version: 1.0
Name: BinomialdistributionsAN
Version: 1.6
Summary: Gaussian Binomial distributions
Home-page: UNKNOWN
Author:  Aymar A. NAHUM 
Author-email: postmaster@jecorde.net
License: UNKNOWN
Platform: UNKNOWN
